folioclient/FolioClient.py
folioclient/__init__.py
folioclient/_httpx.py
folioclient/cached_property.py
folioclient/decorators.py
folioclient/exceptions.py
folioclient-1.0.4.dist-info/WHEEL
folioclient-1.0.4.dist-info/METADATA
folioclient-1.0.4.dist-info/RECORD
