Metadata-Version: 2.4
Name: folioclient
Version: 1.0.4
Summary: An API wrapper over the FOLIO LSP API Suite (Formerly OKAPI).
Keywords: FOLIO,ILS,LSP,Library Systems,MARC21,Library data
Author: Theodor Tolstoy, Brooks Travis
Author-email: Theodor Tolstoy <github.teddes@tolstoy.se>, Brooks Travis <brooks.travis@gmail.com>
License-Expression: MIT
Classifier: Development Status :: 5 - Production/Stable
Classifier: License :: OSI Approved :: MIT License
Classifier: Intended Audience :: Developers
Classifier: Intended Audience :: Information Technology
Classifier: Intended Audience :: System Administrators
Classifier: Programming Language :: Python :: 3
Classifier: Programming Language :: Python :: 3.10
Classifier: Programming Language :: Python :: 3.11
Classifier: Programming Language :: Python :: 3.12
Classifier: Programming Language :: Python :: 3.13
Classifier: Programming Language :: Python :: 3.14
Requires-Dist: httpx>=0.28.1
Requires-Dist: jsonref>=1.1.0
Requires-Dist: py-openapi-schema-to-json-schema>=0.0.3
Requires-Dist: python-dateutil>=2.9.0.post0
Requires-Dist: pyyaml>=6.0.2
Requires-Dist: tenacity>=9.0.0
Requires-Dist: orjson>=3.11.3,<4.0.0 ; extra == 'orjson'
Requires-Python: >=3.10, <4.0
Project-URL: homepage, https://github.com/FOLIO-FSE/folioclient
Provides-Extra: orjson
